Workbook

Sheet Main
A1: OrderID | B1: Day | C1: Month | D1: Year | E1: CustomerID | F1: CustomerName | G1: Region | H1: Category | I1: ProductName | J1: Quantity | K1: UnitPrice | L1: Revenue | M1: Discount% | N1: Disc_amount | O1: TotalAmount | P1: PaymentMethod | Q1: CustomerType
A2: ORD-2025001 | B2: 1 Wed | C2: Jan | D2: 2025 | E2: CUST-1039 | F2: Aarav Joshi | G2: North | H2: Stationery | I2: Gel Pen Pack | J2: 2 | K2: 99 | L2: =Table1[[#This Row],[Quantity]] * Table1[[#This Row],[UnitPrice]] -> 198 | M2: 0 | N2: =Table1[[#This Row],[Revenue]]*Table1[[#This Row],[Discount%]]/100 -> 0 | O2: 198 | P2: Credit Card | Q2: Returning
A3: ORD-2025002 | B3: 1 Wed | C3: Jan | D3: 2025 | E3: CUST-1212 | F3: Komal Joshi | G3: East | H3: Stationery | I3: Notebook Set | J3: 3 | K3: 199 | L3: =Table1[[#This Row],[Quantity]] * Table1[[#This Row],[UnitPrice]] -> 597 | M3: 15 | N3: =Table1[[#This Row],[Revenue]]*Table1[[#This Row],[Discount%]]/100 -> 89.55 | O3: =Table1[[#This Row],[Revenue]]-Table1[[#This Row],[Disc_amount]] -> 507.45 | P3: Debit Card | Q3: New
A4: ORD-2025003 | B4: 1 Wed | C4: Jan | D4: 2025 | E4: CUST-1132 | F4: Shreya Sharma | G4: West | H4: Electronics | I4: Wireless Mouse | J4: 1 | K4: 599 | L4: =Table1[[#This Row],[Quantity]] * Table1[[#This Row],[UnitPrice]] -> 599 | M4: 0 | N4: =Table1[[#This Row],[Revenue]]*Table1[[#This Row],[Discount%]]/100 -> 0 | O4: =Table1[[#This Row],[Revenue]]-Table1[[#This Row],[Disc_amount]] -> 599 | P4: UPI | Q4: New
A5: ORD-2025004 | B5: 1 Wed | C5: Jan | D5: 2025 | E5: CUST-1272 | F5: Aarav Saxena | G5: South | H5: Beauty | I5: Herbal Shampoo | J5: 1 | K5: 249 | L5: =Table1[[#This Row],[Quantity]] * Table1[[#This Row],[UnitPrice]] -> 249 | M5: 15 | N5: =Table1[[#This Row],[Revenue]]*Table1[[#This Row],[Discount%]]/100 -> 37.35 | O5: =Table1[[#This Row],[Revenue]]-Table1[[#This Row],[Disc_amount]] -> 211.65 | P5: Credit Card | Q5: Returning
A6: ORD-2025005 | B6: 1 Wed | C6: Jan | D6: 2025 | E6: CUST-1083 | F6: Komal Kapoor | G6: East | H6: Electronics | I6: Smartwatch | J6: 1 | K6: 2999 | L6: =Table1[[#This Row],[Quantity]] * Table1[[#This Row],[UnitPrice]] -> 2999 | M6: 0 | N6: =Table1[[#This Row],[Revenue]]*Table1[[#This Row],[Discount%]]/100 -> 0 | O6: =Table1[[#This Row],[Revenue]]-Table1[[#This Row],[Disc_amount]] -> 2999 | P6: Cash | Q6: Returning
A7: ORD-2025006 | B7: 1 Wed | C7: Jan | D7: 2025 | E7: CUST-1013 | F7: Divya Joshi | G7: Central | H7: Home & Kitchen | I7: Non-stick Pan Set | J7: 1 | K7: 1299 | L7: =Table1[[#This Row],[Quantity]] * Table1[[#This Row],[UnitPrice]] -> 1299 | M7: 0 | N7: =Table1[[#This Row],[Revenue]]*Table1[[#This Row],[Discount%]]/100 -> 0 | O7: =Table1[[#This Row],[Revenue]]-Table1[[#This Row],[Disc_amount]] -> 1299 | P7: Credit Card | Q7: Returning
A8: ORD-2025007 | B8: 1 Wed | C8: Jan | D8: 2025 | E8: CUST-1166 | F8: Divya Mehta | G8: South | H8: Home & Kitchen | I8: LED Desk Lamp | J8: 2 | K8: 799 | L8: =Table1[[#This Row],[Quantity]] * Table1[[#This Row],[UnitPrice]] -> 1598 | M8: 0 | N8: =Table1[[#This Row],[Revenue]]*Table1[[#This Row],[Discount%]]/100 -> 0 | O8: =Table1[[#This Row],[Revenue]]-Table1[[#This Row],[Disc_amount]] -> 1598 | P8: Debit Card | Q8: New
A9: ORD-2025008 | B9: 2 Thu | C9: Jan | D9: 2025 | E9: CUST-1212 | F9: Komal Joshi | G9: East | H9: Apparel | I9: Denim Jacket | J9: 1 | K9: 1999 | L9: =Table1[[#This Row],[Quantity]] * Table1[[#This Row],[UnitPrice]] -> 1999 | M9: 0 | N9: =Table1[[#This Row],[Revenue]]*Table1[[#This Row],[Discount%]]/100 -> 0 | O9: =Table1[[#This Row],[Revenue]]-Table1[[#This Row],[Disc_amount]] -> 1999 | P9: UPI | Q9: Returning
A10: ORD-2025009 | B10: 2 Thu | C10: Jan | D10: 2025 | E10: CUST-1125 | F10: Muskan Malhotra | G10: North | H10: Groceries | I10: Organic Honey 500g | J10: 1 | K10: 349 | L10: =Table1[[#This Row],[Quantity]] * Table1[[#This Row],[UnitPrice]] -> 349 | M10: 0 | N10: =Table1[[#This Row],[Revenue]]*Table1[[#This Row],[Discount%]]/100 -> 0 | O10: =Table1[[#This Row],[Revenue]]-Table1[[#This Row],[Disc_amount]] -> 349 | P10: Credit Card | Q10: Returning
A11: ORD-2025010 | B11: 2 Thu | C11: Jan | D11: 2025 | E11: CUST-1317 | F11: Aditya Kapoor | G11: North | H11: Home & Kitchen | I11: Non-stick Pan Set | J11: 4 | K11: 1299 | L11: =Table1[[#This Row],[Quantity]] * Table1[[#This Row],[UnitPrice]] -> 5196 | M11: 5 | N11: =Table1[[#This Row],[Revenue]]*Table1[[#This Row],[Discount%]]/100 -> 259.8 | O11: =Table1[[#This Row],[Revenue]]-Table1[[#This Row],[Disc_amount]] -> 4936.2 | P11: Debit Card | Q11: Returning
A12: ORD-2025011 | B12: 2 Thu | C12: Jan | D12: 2025 | E12: CUST-1369 | F12: Rohan Sharma | G12: South | H12: Apparel | I12: Denim Jacket | J12: 2 | K12: 1999 | L12: =Table1[[#This Row],[Quantity]] * Table1[[#This Row],[UnitPrice]] -> 3998 | M12: 0 | N12: =Table1[[#This Row],[Revenue]]*Table1[[#This Row],[Discount%]]/100 -> 0 | O12: =Table1[[#This Row],[Revenue]]-Table1[[#This Row],[Disc_amount]] -> 3998 | P12: UPI | Q12: Returning
A13: ORD-2025012 | B13: 2 Thu | C13: Jan | D13: 2025 | E13: CUST-1250 | F13: Shreya Saxena | G13: Central | H13: Electronics | I13: Smartwatch | J13: 4 | K13: 2999 | L13: =Table1[[#This Row],[Quantity]] * Table1[[#This Row],[UnitPrice]] -> 11996 | M13: 0 | N13: =Table1[[#This Row],[Revenue]]*Table1[[#This Row],[Discount%]]/100 -> 0 | O13: =Table1[[#This Row],[Revenue]]-Table1[[#This Row],[Disc_amount]] -> 11996 | P13: UPI | Q13: Returning
A14: ORD-2025013 | B14: 2 Thu | C14: Jan | D14: 2025 | E14: CUST-1159 | F14: Isha Kapoor | G14: North | H14: Electronics | I14: Wireless Mouse | J14: 2 | K14: 599 | L14: =Table1[[#This Row],[Quantity]] * Table1[[#This Row],[UnitPrice]] -> 1198 | M14: 15 | N14: =Table1[[#This Row],[Revenue]]*Table1[[#This Row],[Discount%]]/100 -> 179.7 | O14: =Table1[[#This Row],[Revenue]]-Table1[[#This Row],[Disc_amount]] -> 1018.3 | P14: Debit Card | Q14: Returning
... A2989: ORD-2027988 | B2989: 31 Wed | C2989: Dec | D2989: 2025 | E2989: CUST-1033 | F2989: Meera Joshi | G2989: East | H2989: Beauty | I2989: Herbal Shampoo | J2989: 1 | K2989: 249 | L2989: =Table1[[#This Row],[Quantity]] * Table1[[#This Row],[UnitPrice]] -> 249 | M2989: 5 | N2989: =Table1[[#This Row],[Revenue]]*Table1[[#This Row],[Discount%]]/100 -> 12.45 | O2989: =Table1[[#This Row],[Revenue]]-Table1[[#This Row],[Disc_amount]] -> 236.55 | P2989: UPI | Q2989: Returning

Sheet KPI
A1: SUMMARY | B1: VALUE
A2: Total Revenue | B2: =SUM(Table1[TotalAmount]) -> 4583605.1
A3: Total Orders | B3: =COUNTA(Main!A:A)-1 -> 2988
A4: Total Customers | B4: =COUNTA(_xlfn.UNIQUE(Main!F:F)) -> 177
A5: Average Revenue Per Customer | B5: =B2/B4 -> 25896.074
A6: Average Order Per Customer | B6: =B3/B4 -> 16.881356
A7: Average Order Value | B7: =AVERAGE(Main!O:O) -> 1534.0044
A8: Average Discount_Percentage | B8: =AVERAGE(Main!M:M)/100 -> 0.10731258
A9: Average Discount_amount | B9: =AVERAGE(Main!N:N) -> 183.25967
A10: Highest Order Value | B10: =MAX(Main!O:O) -> 13495.5
A11: Highest order product Name | B11: =INDEX(Main!I:I,MATCH(KPI!B10,Main!O:O,0)) -> Smartwatch
A12: Lowest Order Value | B12: =MIN(Main!O:O) -> 69.3
A13: Lowest order product Name | B13: =INDEX(Main!I:I,MATCH(KPI!B12,Main!O:O,0)) -> Gel Pen Pack
A14: New Customer Revenue | B14: =SUMIFS(Main!O:O,Main!Q:Q,"New") -> 1664872.7
A15: Returning Customer Revenue | B15: =SUMIFS(Main!O:O,Main!Q:Q,"Returning") -> 2918732.4
A16: Total Discount Given | B16: =SUM(Main!N:N) -> 547579.9
A17: Discount as Per Revenue | B17: =B16/B2 -> 0.11946489

Sheet Charts
H1: BrightRetail FY2025

Sheet Pivot_Table
A1: Monthly-Wise_Sales Summary | D1: Region-wise Performance | I1: Category-wise Analysis | N1: Top 10 Products by Revenue | U1: Customer Analysis
A2: Month | B2: Sum of TotalAmount | D2: Region | E2: Sum of TotalAmount | F2: Average of TotalAmount2 | G2: Count of OrderID | I2: Category | J2: Sum of TotalAmount | K2: Average of Disc_amount | L2: Average of TotalAmount2 | N2: ProductName | O2: Sum of TotalAmount | P2: Sum of Quantity | S2: CustomerType | T2: Values
A3: Jan | B3: 316312.85 | D3: East | E3: 995121.8 | F3: 1523.9231 | G3: 653 | I3: Stationery | J3: 106236.45 | K3: 32.497689 | L3: 258.48285 | N3: Smartwatch | O3: 984721.65 | P3: 366 | S3: New | U3: Returning | W3: Total Count of OrderID | X3: Total Sum of TotalAmount
A4: Feb | B4: 252626.4 | D4: West | E4: 938746.65 | F4: 1641.1655 | G4: 572 | I4: Beauty | J4: 170091.6 | K4: 53.885399 | L4: 468.5719 | N4: Denim Jacket | O4: 556821.45 | P4: 315 | R4: Region | S4: Count of OrderID | T4: Sum of TotalAmount | U4: Count of OrderID | V4: Sum of TotalAmount
A5: Mar | B5: 314403 | D5: Central | E5: 933396.6 | F5: 1566.1017 | G5: 596 | I5: Groceries | J5: 270868.55 | K5: 87.726751 | L5: 758.73543 | N5: Bluetooth Headphones | O5: 537541.2 | P5: 335 | R5: Central | S5: 215 | T5: 344976.7 | U5: 381 | V5: 588419.9 | W5: 596 | X5: 933396.6
A6: Apr | B6: 291536.2 | D6: South | E6: 882788.5 | F6: 1543.3365 | G6: 572 | I6: Home & Kitchen | J6: 612745.1 | K6: 196.08283 | L6: 1697.3548 | N6: Cricket Bat | O6: 522251.6 | P6: 391 | R6: East | S6: 234 | T6: 377547.3 | U6: 419 | V6: 617574.5 | W6: 653 | X6: 995121.8
A7: May | B7: 348393.7 | D7: North | E7: 833551.55 | F7: 1400.927 | G7: 595 | I7: Sports | J7: 737788.25 | K7: 222.82712 | L7: 1896.6279 | N7: Non-stick Pan Set | O7: 346638.15 | P7: 298 | R7: North | S7: 204 | T7: 283236.6 | U7: 391 | V7: 550314.95 | W7: 595 | X7: 833551.55
A8: Jun | B8: 450418.25 | D8: Grand Total | E8: 4583605.1 | F8: 1534.0044 | G8: 2988 | I8: Apparel | J8: 970794.2 | K8: 232.74962 | L8: 1824.8011 | N8: Formal Shirt | O8: 266193.9 | P8: 329 | R8: South | S8: 195 | T8: 344311.1 | U8: 377 | V8: 538477.4 | W8: 572 | X8: 882788.5
A9: Jul | B9: 292230.85 | I9: Electronics | J9: 1715081 | K9: 351.40183 | L9: 2982.7495 | N9: LED Desk Lamp | O9: 266106.95 | P9: 371 | R9: West | S9: 197 | T9: 314800.95 | U9: 375 | V9: 623945.7 | W9: 572 | X9: 938746.65
A10: Aug | B10: 338460.65 | I10: Grand Total | J10: 4583605.1 | K10: 183.25967 | L10: 1534.0044 | N10: Yoga Mat | O10: 215536.65 | P10: 341 | R10: Grand Total | S10: 1045 | T10: 1664872.7 | U10: 1943 | V10: 2918732.4 | W10: 2988 | X10: 4583605.1
A11: Sep | B11: 400044.95 | D11: Payment Method Distribution | N11: Wireless Mouse | O11: 192818.1 | P11: 362
A12: Oct | B12: 459198.55 | D12: PaymentMethod | E12: Sum of TotalAmount | F12: Count of OrderID | N12: Basmati Rice 5kg | O12: 174527.1 | P12: 354
A13: Nov | B13: 517464.4 | D13: UPI | E13: 1200164.4 | F13: 728 | N13: Grand Total | O13: 4063156.7 | P13: 3462
A14: Dec | B14: 602515.3 | D14: Debit Card | E14: 1156478.7 | F14: 755
A15: Grand Total | B15: 4583605.1 | D15: Credit Card | E15: 1024706.5 | F15: 753
D16: Cash | E16: 701030.25 | F16: 436
D17: Net Banking | E17: 501225.3 | F17: 316
D18: Grand Total | E18: 4583605.1 | F18: 2988
